collect/__init__.py
collect/admin.py
collect/apps.py
collect/serializers.py
collect/urls.py
collect/utilities.py
collect/migrations/0001_initial.py
collect/migrations/__init__.py
collect/models/SKU.py
collect/models/__init__.py
collect/models/address.py
collect/models/card_to_card.py
collect/models/checkout_page.py
collect/models/client_details.py
collect/models/coupon.py
collect/models/customer.py
collect/models/customer_payment_method.py
collect/models/discount.py
collect/models/dispute.py
collect/models/escrow.py
collect/models/group_payment.py
collect/models/hosted_page_card_token.py
collect/models/invoice.py
collect/models/invoiceItem.py
collect/models/order.py
collect/models/orderReturn.py
collect/models/outcome.py
collect/models/payment.py
collect/models/paymentFees.py
collect/models/payment_method_data.py
collect/models/payment_method_type.py
collect/models/planCollect.py
collect/models/product.py
collect/models/refund.py
collect/models/suscriptionCollect.py
collect/models/suscriptionItem.py
collect/models/usageRecord.py
collect/tests/__init__.py
collect/tests/test_checkout.py
collect/tests/test_dispute.py
collect/tests/test_escrow.py
collect/tests/test_group.py
collect/tests/test_payment.py
collect/tests/test_refund.py
collect/views/__init__.py
collect/views/cardToCardView.py
collect/views/checkoutView.py
collect/views/disputeView.py
collect/views/escrowView.py
collect/views/groupPaymentView.py
collect/views/paymentView.py
collect/views/refundView.py
rapyd_site/__init__.py
rapyd_site/asgi.py
rapyd_site/settings.py
rapyd_site/urls.py
rapyd_site/wsgi.py
collectapp-0.0.3.dist-info/LICENSE
collectapp-0.0.3.dist-info/METADATA
collectapp-0.0.3.dist-info/WHEEL
collectapp-0.0.3.dist-info/top_level.txt
collectapp-0.0.3.dist-info/RECORD
