Metadata-Version: 2.1
Name: collectapp
Version: 0.0.3
Summary: Integracion de rapyd
Author: Juan Hector Manuel
Author-email: 
License: UNKNOWN
Platform: UNKNOWN
Classifier: Programming Language :: Python :: 3
Classifier: License :: OSI Approved :: MIT License
Classifier: Operating System :: OS Independent
Requires-Python: >=3.6
License-File: LICENSE
